{
  "Tech": {
    "Headphones": [
      "airpods", "airpod", "air pods", "air pod", "apple earbuds", "apple earpods",
      "airpods pro", "airpods max", "airpods 2", "airpods 3", "airpods pro 2",
      "airpods 2nd generation", "airpods 3rd generation", "airpods pro 2nd generation",
      "airpods magsafe", "airpods lightning", "airpods usb-c", "airpods wireless",
      "airpds", "aripos", "aripods", "apods", "ap pods", "apple airpads", "air buds",
      "beats", "beats headphones", "beats solo", "beats studio", "beats pro",
      "beats solo 3", "beats solo3", "beats studio 3", "beats studio3",
      "beats studio buds", "beats fit pro", "powerbeats", "powerbeats pro",
      "beats x", "beatsx", "urbeats", "beats ep", "beats mixr",
      "beets", "bats headphones", "beatz", "beat headphones",
      "bose", "bose headphones", "bose quietcomfort", "bose qc", "bose nc",
      "bose qc35", "bose qc45", "bose qc25", "bose 700", "bose nc 700",
      "bose soundsport", "bose quietcomfort 35", "bose quietcomfort 45",
      "boss headphones", "boze", "bosee", "quiet comfort",
      "sony wh", "sony wf", "sony headphones", "sony earbuds", "sony xm4", "sony xm5",
      "sony wh-1000xm4", "sony wh-1000xm5", "sony wf-1000xm4", "sony wf-1000xm5",
      "sony linkbuds", "sony extra bass", "sony xb", "sony wh-ch710n",
      "sonny headphones", "soney", "sony x1000",
      "gaming headset", "gaming headphones", "pc gaming headset", "xbox headset",
      "steelseries arctis", "hyperx cloud", "razer kraken", "logitech g pro",
      "turtle beach", "astro a40", "astro a50", "sennheiser game",
      "wireless headphones", "bluetooth headphones", "bluetooth earbuds",
      "noise cancelling headphones", "anc headphones", "true wireless",
      "over ear headphones", "on ear headphones", "in ear headphones"
    ],
    "Smartphones": [
      "iphone", "iphone 15", "iphone 15 pro", "iphone 15 pro max", "iphone 15 plus",
      "iphone 14", "iphone 14 pro", "iphone 14 pro max", "iphone 14 plus",
      "iphone 13", "iphone 13 pro", "iphone 13 pro max", "iphone 13 mini",
      "iphone 12", "iphone 12 pro", "iphone 12 pro max", "iphone 12 mini",
      "iphone 11", "iphone 11 pro", "iphone 11 pro max", "iphone se",
      "iphone se 2022", "iphone xr", "iphone xs", "iphone x",
      "iphone black", "iphone white", "iphone blue", "iphone red", "iphone purple",
      "iphone 128gb", "iphone 256gb", "iphone 512gb", "iphone 1tb", "iphone unlocked",
      "ifone", "i phone", "apple phone", "iphome",
      "samsung galaxy", "galaxy s24", "galaxy s23", "galaxy s22", "galaxy s21",
      "galaxy s24 ultra", "galaxy s23 ultra", "galaxy s22 ultra",
      "galaxy s24 plus", "galaxy note", "galaxy z fold", "galaxy z flip",
      "galaxy a54", "galaxy a53", "galaxy a52", "samsung s24", "samsung phone",
      "samung", "samsung galxy", "galxy",
      "google pixel", "pixel 8", "pixel 8 pro", "pixel 7", "pixel 7 pro",
      "pixel 7a", "pixel 6", "pixel 6 pro", "pixel 6a", "pixel phone",
      "oneplus", "oneplus 12", "oneplus 11", "oneplus nord", "xiaomi", "redmi",
      "huawei", "honor", "oppo", "vivo", "realme", "motorola", "moto g"
    ],
    "Laptops": [
      "macbook", "macbook pro", "macbook air", "mac book", "macbook m3", "macbook m2",
      "macbook pro 16", "macbook pro 14", "macbook pro 13", "macbook air 15",
      "macbook pro m3", "macbook pro m2", "macbook air m3", "macbook air m2",
      "macbook 2024", "macbook 2023", "macbook space gray", "macbook silver",
      "macbook 256gb", "macbook 512gb", "macbook 1tb", "macbook 16gb", "macbook 32gb",
      "mackbook", "macbok", "mac book pro", "apple laptop",
      "gaming laptop", "rog laptop", "asus rog", "legion laptop", "msi gaming",
      "alienware", "razer blade", "predator laptop", "hp omen", "dell g15",
      "rog strix", "rog zephyrus", "legion 5", "legion 7", "msi katana",
      "alienware m15", "razer blade 15", "predator helios", "acer nitro",
      "rtx 4090 laptop", "rtx 4080 laptop", "rtx 4070 laptop", "rtx 3080 laptop",
      "gaming laptop 144hz", "gaming laptop 240hz", "gaming notebook",
      "thinkpad", "dell xps", "hp elitebook", "surface laptop", "business laptop",
      "thinkpad x1", "thinkpad carbon", "dell xps 13", "dell xps 15",
      "surface laptop 5", "hp spectre", "lenovo yoga", "2-in-1 laptop"
    ],
    "Graphics Cards": [
      "rtx 4090", "rtx 4080", "rtx 4070", "rtx 4060", "rtx 4070 ti", "rtx 4060 ti",
      "geforce rtx 4090", "nvidia rtx 4090", "rtx 4090 24gb", "rtx 4080 16gb",
      "rtx 3090", "rtx 3080", "rtx 3070", "rtx 3060", "rtx 3050", "rtx 3090 ti",
      "rtx 3080 ti", "rtx 3070 ti", "rtx 3060 ti", "rtx 3090 24gb", "rtx 3080 10gb",
      "rx 7900 xtx", "rx 7900 xt", "rx 7800 xt", "rx 7700 xt", "rx 7600",
      "rx 6950 xt", "rx 6900 xt", "rx 6800 xt", "rx 6800", "rx 6750 xt",
      "radeon rx", "amd radeon", "amd gpu", "asus gpu", "msi gpu", "gigabyte gpu",
      "graphics card", "video card", "gpu", "gaming gpu", "founders edition"
    ],
    "Tablets": [
      "ipad", "ipad pro", "ipad air", "ipad mini", "apple ipad", "ipad 2024",
      "ipad pro 12.9", "ipad pro 11", "ipad air 5", "ipad 10th generation",
      "ipad 64gb", "ipad 256gb", "ipad 512gb", "ipad 1tb", "ipad wifi", "ipad cellular",
      "samsung galaxy tab", "galaxy tab s9", "galaxy tab s8", "galaxy tab a8",
      "microsoft surface", "surface pro", "surface go", "kindle fire", "amazon fire"
    ]
  },
  "Gaming": {
    "Consoles": [
      "playstation 5", "ps5", "ps5 console", "ps5 disc", "ps5 digital",
      "ps5 bundle", "ps5 controller", "ps5 games", "ps5 slim", "ps5 pro",
      "playstation 4", "ps4", "ps4 pro", "ps4 slim", "ps4 console",
      "playstaton", "play station", "ps 5", "playstation5",
      "xbox series x", "xbox series s", "xbox sx", "xbox ss", "xbox console",
      "xbox one", "xbox one x", "xbox one s", "xbox 360", "xbox controller",
      "x box", "xobx", "xbox seriex x", "microsoft xbox",
      "nintendo switch", "switch oled", "switch lite", "nintendo switch oled",
      "switch console", "switch pro controller", "joy con", "joycon",
      "nintendo 3ds", "3ds xl", "2ds", "gameboy", "wii", "wii u",
      "nintedo", "nintndo", "nintendo swich", "joy-con",
      "steam deck", "valve steam deck", "rog ally", "handheld gaming"
    ],
    "Video Games": [
      "call of duty", "cod", "modern warfare", "warzone", "black ops",
      "fifa 24", "madden 24", "nba 2k24", "grand theft auto", "gta",
      "elder scrolls", "skyrim", "fallout", "witcher 3", "cyberpunk 2077",
      "spider-man", "god of war", "last of us", "uncharted", "horizon",
      "zelda", "
